gnay-0.1.2.dist-info/DESCRIPTION.rst
gnay-0.1.2.dist-info/METADATA
gnay-0.1.2.dist-info/RECORD
gnay-0.1.2.dist-info/WHEEL
gnay-0.1.2.dist-info/entry_points.txt
gnay-0.1.2.dist-info/metadata.json
gnay-0.1.2.dist-info/top_level.txt
gnay-0.1.2.dist-info/zip-safe
me/__init__.py
me/me.py
