Metadata-Version: 2.0
Name: gnay
Version: 0.1.2
Summary: desc me
Home-page: UNKNOWN
Author: yang
Author-email: UNKNOWN
License: UNKNOWN
Keywords: me
Platform: UNKNOWN
